{
  "generatedAt": "2026-01-05T13:55:46.917Z",
  "label": "全部年级",
  "total": 38093,
  "yearStats": {
    "2021": {
      "total": 6377,
      "male": 4091,
      "female": 2286,
      "ratio": "1.79"
    },
    "2022": {
      "total": 6717,
      "male": 4367,
      "female": 2350,
      "ratio": "1.86"
    },
    "2023": {
      "total": 8878,
      "male": 5162,
      "female": 3716,
      "ratio": "1.39"
    },
    "2024": {
      "total": 8454,
      "male": 5068,
      "female": 3386,
      "ratio": "1.50"
    },
    "2025": {
      "total": 7667,
      "male": 4308,
      "female": 3359,
      "ratio": "1.28"
    }
  },
  "gender": {
    "male": 22996,
    "female": 15097,
    "ratio": "1.52",
    "malePercent": "60.4",
    "femalePercent": "39.6"
  },
  "surnames": [
    {
      "name": "王",
      "count": 3508
    },
    {
      "name": "李",
      "count": 3253
    },
    {
      "name": "张",
      "count": 3205
    },
    {
      "name": "刘",
      "count": 2091
    },
    {
      "name": "陈",
      "count": 1343
    },
    {
      "name": "杨",
      "count": 1211
    },
    {
      "name": "赵",
      "count": 1025
    },
    {
      "name": "郭",
      "count": 710
    },
    {
      "name": "周",
      "count": 640
    },
    {
      "name": "马",
      "count": 613
    },
    {
      "name": "吴",
      "count": 565
    },
    {
      "name": "孙",
      "count": 563
    },
    {
      "name": "黄",
      "count": 543
    },
    {
      "name": "朱",
      "count": 507
    },
    {
      "name": "高",
      "count": 452
    },
    {
      "name": "徐",
      "count": 452
    },
    {
      "name": "胡",
      "count": 433
    },
    {
      "name": "宋",
      "count": 385
    },
    {
      "name": "郑",
      "count": 362
    },
    {
      "name": "韩",
      "count": 340
    },
    {
      "name": "何",
      "count": 283
    },
    {
      "name": "冯",
      "count": 272
    },
    {
      "name": "曹",
      "count": 271
    },
    {
      "name": "梁",
      "count": 267
    },
    {
      "name": "魏",
      "count": 261
    },
    {
      "name": "程",
      "count": 236
    },
    {
      "name": "任",
      "count": 234
    },
    {
      "name": "贾",
      "count": 233
    },
    {
      "name": "崔",
      "count": 231
    },
    {
      "name": "董",
      "count": 224
    },
    {
      "name": "杜",
      "count": 222
    },
    {
      "name": "田",
      "count": 220
    },
    {
      "name": "罗",
      "count": 219
    },
    {
      "name": "袁",
      "count": 218
    },
    {
      "name": "许",
      "count": 218
    },
    {
      "name": "吕",
      "count": 206
    },
    {
      "name": "谢",
      "count": 199
    },
    {
      "name": "于",
      "count": 195
    },
    {
      "name": "闫",
      "count": 190
    },
    {
      "name": "丁",
      "count": 181
    },
    {
      "name": "范",
      "count": 177
    },
    {
      "name": "林",
      "count": 176
    },
    {
      "name": "侯",
      "count": 172
    },
    {
      "name": "苏",
      "count": 170
    },
    {
      "name": "秦",
      "count": 168
    },
    {
      "name": "彭",
      "count": 162
    },
    {
      "name": "邓",
      "count": 158
    },
    {
      "name": "余",
      "count": 158
    },
    {
      "name": "付",
      "count": 155
    },
    {
      "name": "卢",
      "count": 149
    }
  ],
  "rareNames": [
    {
      "name": "濮",
      "count": 3
    },
    {
      "name": "阙",
      "count": 3
    },
    {
      "name": "水",
      "count": 3
    },
    {
      "name": "庆",
      "count": 3
    },
    {
      "name": "戈",
      "count": 3
    },
    {
      "name": "芮",
      "count": 3
    },
    {
      "name": "介",
      "count": 3
    },
    {
      "name": "奚",
      "count": 3
    },
    {
      "name": "化",
      "count": 3
    },
    {
      "name": "堵",
      "count": 3
    },
    {
      "name": "晏",
      "count": 3
    },
    {
      "name": "屠",
      "count": 3
    },
    {
      "name": "储",
      "count": 3
    },
    {
      "name": "展",
      "count": 3
    },
    {
      "name": "滑",
      "count": 3
    },
    {
      "name": "毋",
      "count": 3
    },
    {
      "name": "铁",
      "count": 3
    },
    {
      "name": "慕",
      "count": 3
    },
    {
      "name": "郄",
      "count": 3
    },
    {
      "name": "雍",
      "count": 3
    },
    {
      "name": "哈",
      "count": 3
    },
    {
      "name": "冶",
      "count": 3
    },
    {
      "name": "酒",
      "count": 3
    },
    {
      "name": "帅",
      "count": 3
    },
    {
      "name": "迟",
      "count": 3
    },
    {
      "name": "花",
      "count": 3
    },
    {
      "name": "生",
      "count": 3
    },
    {
      "name": "封",
      "count": 3
    },
    {
      "name": "靖",
      "count": 3
    },
    {
      "name": "瓮",
      "count": 3
    }
  ],
  "duplicateNames": [
    {
      "name": "王硕",
      "count": 23
    },
    {
      "name": "王浩",
      "count": 21
    },
    {
      "name": "刘畅",
      "count": 18
    },
    {
      "name": "李硕",
      "count": 16
    },
    {
      "name": "王子涵",
      "count": 14
    },
    {
      "name": "李想",
      "count": 14
    },
    {
      "name": "王涵",
      "count": 13
    },
    {
      "name": "刘硕",
      "count": 13
    },
    {
      "name": "张硕",
      "count": 13
    },
    {
      "name": "王浩宇",
      "count": 13
    },
    {
      "name": "张博",
      "count": 12
    },
    {
      "name": "王一鸣",
      "count": 12
    },
    {
      "name": "刘洋",
      "count": 11
    },
    {
      "name": "王旭",
      "count": 11
    },
    {
      "name": "李翔",
      "count": 10
    },
    {
      "name": "张宇航",
      "count": 10
    },
    {
      "name": "李鑫",
      "count": 10
    },
    {
      "name": "张家豪",
      "count": 10
    },
    {
      "name": "张豪",
      "count": 10
    },
    {
      "name": "王浩然",
      "count": 10
    },
    {
      "name": "李博",
      "count": 10
    },
    {
      "name": "李阳",
      "count": 9
    },
    {
      "name": "张子豪",
      "count": 9
    },
    {
      "name": "王宇",
      "count": 9
    },
    {
      "name": "李杰",
      "count": 9
    },
    {
      "name": "王博",
      "count": 9
    },
    {
      "name": "刘宇轩",
      "count": 9
    },
    {
      "name": "张扬",
      "count": 9
    },
    {
      "name": "张佳怡",
      "count": 9
    },
    {
      "name": "王梦瑶",
      "count": 9
    },
    {
      "name": "张凯",
      "count": 9
    },
    {
      "name": "刘翔",
      "count": 9
    },
    {
      "name": "张涛",
      "count": 8
    },
    {
      "name": "王俊杰",
      "count": 8
    },
    {
      "name": "杨晨",
      "count": 8
    },
    {
      "name": "张涵",
      "count": 8
    },
    {
      "name": "张旭",
      "count": 8
    },
    {
      "name": "张杰",
      "count": 8
    },
    {
      "name": "李世豪",
      "count": 8
    },
    {
      "name": "刘鑫",
      "count": 8
    },
    {
      "name": "刘子涵",
      "count": 8
    },
    {
      "name": "李浩然",
      "count": 8
    },
    {
      "name": "陈文博",
      "count": 8
    },
    {
      "name": "张文杰",
      "count": 8
    },
    {
      "name": "王杰",
      "count": 8
    },
    {
      "name": "张浩",
      "count": 8
    },
    {
      "name": "张博文",
      "count": 8
    },
    {
      "name": "陈卓",
      "count": 7
    },
    {
      "name": "王璐",
      "count": 7
    },
    {
      "name": "李佳",
      "count": 7
    }
  ],
  "topDuplicates": [
    {
      "name": "王硕",
      "count": 23
    },
    {
      "name": "王浩",
      "count": 21
    },
    {
      "name": "刘畅",
      "count": 18
    },
    {
      "name": "李硕",
      "count": 16
    },
    {
      "name": "王子涵",
      "count": 14
    },
    {
      "name": "李想",
      "count": 14
    },
    {
      "name": "王涵",
      "count": 13
    },
    {
      "name": "刘硕",
      "count": 13
    },
    {
      "name": "张硕",
      "count": 13
    },
    {
      "name": "王浩宇",
      "count": 13
    },
    {
      "name": "张博",
      "count": 12
    },
    {
      "name": "王一鸣",
      "count": 12
    },
    {
      "name": "刘洋",
      "count": 11
    },
    {
      "name": "王旭",
      "count": 11
    },
    {
      "name": "李翔",
      "count": 10
    },
    {
      "name": "张宇航",
      "count": 10
    },
    {
      "name": "李鑫",
      "count": 10
    },
    {
      "name": "张家豪",
      "count": 10
    },
    {
      "name": "张豪",
      "count": 10
    },
    {
      "name": "王浩然",
      "count": 10
    },
    {
      "name": "李博",
      "count": 10
    },
    {
      "name": "李阳",
      "count": 9
    },
    {
      "name": "张子豪",
      "count": 9
    },
    {
      "name": "王宇",
      "count": 9
    },
    {
      "name": "李杰",
      "count": 9
    },
    {
      "name": "王博",
      "count": 9
    },
    {
      "name": "刘宇轩",
      "count": 9
    },
    {
      "name": "张扬",
      "count": 9
    },
    {
      "name": "张佳怡",
      "count": 9
    },
    {
      "name": "王梦瑶",
      "count": 9
    }
  ],
  "nameLength": {
    "distribution": {
      "2": 5951,
      "3": 32002,
      "4": 138,
      "5": 2
    },
    "shortest": {
      "length": 2,
      "names": [
        "袁傲",
        "林潮",
        "罗致",
        "刘彤",
        "孟昕",
        "任俊",
        "李锐",
        "岳蕾",
        "邓潇",
        "钟浩"
      ]
    },
    "longest": {
      "length": 5,
      "names": [
        "阿根么此牛",
        "张英姿格格"
      ]
    }
  },
  "givenNames": {
    "top": [
      {
        "name": "硕",
        "count": 121
      },
      {
        "name": "浩",
        "count": 115
      },
      {
        "name": "鑫",
        "count": 91
      },
      {
        "name": "浩然",
        "count": 90
      },
      {
        "name": "子涵",
        "count": 87
      },
      {
        "name": "博文",
        "count": 86
      },
      {
        "name": "博",
        "count": 82
      },
      {
        "name": "帅",
        "count": 77
      },
      {
        "name": "宇航",
        "count": 75
      },
      {
        "name": "杰",
        "count": 70
      },
      {
        "name": "旭",
        "count": 67
      },
      {
        "name": "一鸣",
        "count": 65
      },
      {
        "name": "一帆",
        "count": 65
      },
      {
        "name": "子豪",
        "count": 64
      },
      {
        "name": "文博",
        "count": 64
      },
      {
        "name": "梦瑶",
        "count": 63
      },
      {
        "name": "涛",
        "count": 61
      },
      {
        "name": "洋",
        "count": 61
      },
      {
        "name": "昊",
        "count": 58
      },
      {
        "name": "晨阳",
        "count": 57
      },
      {
        "name": "佳怡",
        "count": 57
      },
      {
        "name": "婷婷",
        "count": 56
      },
      {
        "name": "晨",
        "count": 55
      },
      {
        "name": "文杰",
        "count": 53
      },
      {
        "name": "俊杰",
        "count": 52
      },
      {
        "name": "凯",
        "count": 52
      },
      {
        "name": "家乐",
        "count": 51
      },
      {
        "name": "畅",
        "count": 51
      },
      {
        "name": "宇",
        "count": 51
      },
      {
        "name": "思雨",
        "count": 50
      },
      {
        "name": "阳",
        "count": 47
      },
      {
        "name": "佳",
        "count": 47
      },
      {
        "name": "翔",
        "count": 47
      },
      {
        "name": "世豪",
        "count": 47
      },
      {
        "name": "磊",
        "count": 47
      },
      {
        "name": "佳乐",
        "count": 47
      },
      {
        "name": "鹏",
        "count": 47
      },
      {
        "name": "涵",
        "count": 46
      },
      {
        "name": "宇轩",
        "count": 46
      },
      {
        "name": "豪",
        "count": 46
      },
      {
        "name": "佳慧",
        "count": 46
      },
      {
        "name": "悦",
        "count": 43
      },
      {
        "name": "家豪",
        "count": 43
      },
      {
        "name": "静怡",
        "count": 43
      },
      {
        "name": "一凡",
        "count": 42
      },
      {
        "name": "雨欣",
        "count": 42
      },
      {
        "name": "欣",
        "count": 42
      },
      {
        "name": "甜甜",
        "count": 42
      },
      {
        "name": "卓",
        "count": 41
      },
      {
        "name": "晴",
        "count": 40
      }
    ],
    "topChars": [
      {
        "char": "宇",
        "count": 1228
      },
      {
        "char": "佳",
        "count": 1189
      },
      {
        "char": "文",
        "count": 1159
      },
      {
        "char": "子",
        "count": 913
      },
      {
        "char": "雨",
        "count": 890
      },
      {
        "char": "博",
        "count": 879
      },
      {
        "char": "浩",
        "count": 861
      },
      {
        "char": "豪",
        "count": 834
      },
      {
        "char": "梦",
        "count": 788
      },
      {
        "char": "杰",
        "count": 698
      },
      {
        "char": "涵",
        "count": 691
      },
      {
        "char": "怡",
        "count": 690
      },
      {
        "char": "鑫",
        "count": 643
      },
      {
        "char": "阳",
        "count": 640
      },
      {
        "char": "欣",
        "count": 630
      },
      {
        "char": "晨",
        "count": 551
      },
      {
        "char": "一",
        "count": 535
      },
      {
        "char": "嘉",
        "count": 531
      },
      {
        "char": "家",
        "count": 525
      },
      {
        "char": "俊",
        "count": 515
      },
      {
        "char": "明",
        "count": 502
      },
      {
        "char": "思",
        "count": 481
      },
      {
        "char": "志",
        "count": 471
      },
      {
        "char": "鹏",
        "count": 458
      },
      {
        "char": "婷",
        "count": 450
      },
      {
        "char": "凯",
        "count": 430
      },
      {
        "char": "晓",
        "count": 418
      },
      {
        "char": "玉",
        "count": 410
      },
      {
        "char": "慧",
        "count": 409
      },
      {
        "char": "洋",
        "count": 404
      },
      {
        "char": "乐",
        "count": 402
      },
      {
        "char": "轩",
        "count": 392
      },
      {
        "char": "航",
        "count": 387
      },
      {
        "char": "瑞",
        "count": 374
      },
      {
        "char": "昊",
        "count": 369
      },
      {
        "char": "龙",
        "count": 364
      },
      {
        "char": "旭",
        "count": 358
      },
      {
        "char": "琪",
        "count": 354
      },
      {
        "char": "林",
        "count": 353
      },
      {
        "char": "天",
        "count": 345
      },
      {
        "char": "静",
        "count": 343
      },
      {
        "char": "雅",
        "count": 338
      },
      {
        "char": "泽",
        "count": 336
      },
      {
        "char": "硕",
        "count": 336
      },
      {
        "char": "辉",
        "count": 330
      },
      {
        "char": "金",
        "count": 325
      },
      {
        "char": "飞",
        "count": 320
      },
      {
        "char": "涛",
        "count": 310
      },
      {
        "char": "翔",
        "count": 307
      },
      {
        "char": "艺",
        "count": 301
      }
    ]
  },
  "genderChars": {
    "male": [
      {
        "char": "宇",
        "count": 1006
      },
      {
        "char": "浩",
        "count": 835
      },
      {
        "char": "豪",
        "count": 829
      },
      {
        "char": "博",
        "count": 826
      },
      {
        "char": "文",
        "count": 793
      },
      {
        "char": "子",
        "count": 620
      },
      {
        "char": "杰",
        "count": 619
      },
      {
        "char": "阳",
        "count": 517
      },
      {
        "char": "俊",
        "count": 460
      },
      {
        "char": "志",
        "count": 442
      },
      {
        "char": "鑫",
        "count": 438
      },
      {
        "char": "鹏",
        "count": 438
      },
      {
        "char": "家",
        "count": 437
      },
      {
        "char": "佳",
        "count": 409
      },
      {
        "char": "明",
        "count": 400
      },
      {
        "char": "凯",
        "count": 384
      },
      {
        "char": "航",
        "count": 362
      },
      {
        "char": "龙",
        "count": 359
      },
      {
        "char": "晨",
        "count": 357
      },
      {
        "char": "昊",
        "count": 351
      },
      {
        "char": "一",
        "count": 350
      },
      {
        "char": "洋",
        "count": 322
      },
      {
        "char": "辉",
        "count": 321
      },
      {
        "char": "轩",
        "count": 320
      },
      {
        "char": "嘉",
        "count": 313
      },
      {
        "char": "旭",
        "count": 308
      },
      {
        "char": "涛",
        "count": 305
      },
      {
        "char": "泽",
        "count": 300
      },
      {
        "char": "翔",
        "count": 300
      },
      {
        "char": "天",
        "count": 297
      },
      {
        "char": "硕",
        "count": 294
      },
      {
        "char": "飞",
        "count": 285
      },
      {
        "char": "林",
        "count": 283
      },
      {
        "char": "帅",
        "count": 278
      },
      {
        "char": "乐",
        "count": 274
      },
      {
        "char": "康",
        "count": 273
      },
      {
        "char": "涵",
        "count": 259
      },
      {
        "char": "世",
        "count": 245
      },
      {
        "char": "恒",
        "count": 239
      },
      {
        "char": "超",
        "count": 238
      },
      {
        "char": "伟",
        "count": 226
      },
      {
        "char": "成",
        "count": 219
      },
      {
        "char": "祥",
        "count": 217
      },
      {
        "char": "雨",
        "count": 213
      },
      {
        "char": "金",
        "count": 212
      },
      {
        "char": "瑞",
        "count": 209
      },
      {
        "char": "哲",
        "count": 208
      },
      {
        "char": "铭",
        "count": 207
      },
      {
        "char": "东",
        "count": 207
      },
      {
        "char": "坤",
        "count": 197
      }
    ],
    "female": [
      {
        "char": "佳",
        "count": 780
      },
      {
        "char": "雨",
        "count": 677
      },
      {
        "char": "梦",
        "count": 638
      },
      {
        "char": "怡",
        "count": 612
      },
      {
        "char": "欣",
        "count": 541
      },
      {
        "char": "婷",
        "count": 449
      },
      {
        "char": "涵",
        "count": 432
      },
      {
        "char": "慧",
        "count": 378
      },
      {
        "char": "文",
        "count": 366
      },
      {
        "char": "思",
        "count": 343
      },
      {
        "char": "静",
        "count": 336
      },
      {
        "char": "雅",
        "count": 327
      },
      {
        "char": "子",
        "count": 293
      },
      {
        "char": "晓",
        "count": 287
      },
      {
        "char": "琪",
        "count": 268
      },
      {
        "char": "莹",
        "count": 262
      },
      {
        "char": "玉",
        "count": 248
      },
      {
        "char": "瑶",
        "count": 233
      },
      {
        "char": "雯",
        "count": 230
      },
      {
        "char": "雪",
        "count": 229
      },
      {
        "char": "彤",
        "count": 223
      },
      {
        "char": "宇",
        "count": 222
      },
      {
        "char": "嘉",
        "count": 218
      },
      {
        "char": "晴",
        "count": 217
      },
      {
        "char": "艺",
        "count": 206
      },
      {
        "char": "鑫",
        "count": 205
      },
      {
        "char": "琳",
        "count": 205
      },
      {
        "char": "颖",
        "count": 196
      },
      {
        "char": "晨",
        "count": 194
      },
      {
        "char": "悦",
        "count": 193
      },
      {
        "char": "茹",
        "count": 191
      },
      {
        "char": "丽",
        "count": 191
      },
      {
        "char": "一",
        "count": 185
      },
      {
        "char": "冰",
        "count": 185
      },
      {
        "char": "洁",
        "count": 184
      },
      {
        "char": "紫",
        "count": 172
      },
      {
        "char": "瑞",
        "count": 165
      },
      {
        "char": "钰",
        "count": 155
      },
      {
        "char": "心",
        "count": 152
      },
      {
        "char": "馨",
        "count": 148
      },
      {
        "char": "菲",
        "count": 144
      },
      {
        "char": "媛",
        "count": 140
      },
      {
        "char": "妍",
        "count": 132
      },
      {
        "char": "丹",
        "count": 130
      },
      {
        "char": "乐",
        "count": 128
      },
      {
        "char": "璐",
        "count": 126
      },
      {
        "char": "倩",
        "count": 125
      },
      {
        "char": "亚",
        "count": 125
      },
      {
        "char": "阳",
        "count": 123
      },
      {
        "char": "月",
        "count": 122
      }
    ]
  },
  "colleges": [
    {
      "name": "设计学类",
      "count": 2365
    },
    {
      "name": "工业软件",
      "count": 1299
    },
    {
      "name": "机制自动化",
      "count": 1228
    },
    {
      "name": "移动软件",
      "count": 1218
    },
    {
      "name": "嵌入式软件",
      "count": 1187
    },
    {
      "name": "网云",
      "count": 1047
    },
    {
      "name": "智能物联",
      "count": 1047
    },
    {
      "name": "能源",
      "count": 892
    },
    {
      "name": "电气工程",
      "count": 848
    },
    {
      "name": "软件工程",
      "count": 728
    },
    {
      "name": "食品科学",
      "count": 685
    },
    {
      "name": "行业应用软件",
      "count": 631
    },
    {
      "name": "新型平台软件",
      "count": 629
    },
    {
      "name": "IEC软件工程",
      "count": 609
    },
    {
      "name": "自动化",
      "count": 591
    },
    {
      "name": "电子科技",
      "count": 590
    },
    {
      "name": "高分子",
      "count": 584
    },
    {
      "name": "计算机",
      "count": 575
    },
    {
      "name": "IEC食品科学",
      "count": 563
    },
    {
      "name": "建筑电气",
      "count": 493
    },
    {
      "name": "新材器",
      "count": 440
    },
    {
      "name": "化工工艺",
      "count": 438
    },
    {
      "name": "应用化学",
      "count": 436
    },
    {
      "name": "会计学",
      "count": 431
    },
    {
      "name": "英语",
      "count": 424
    },
    {
      "name": "软件安全与管理",
      "count": 389
    },
    {
      "name": "经济学",
      "count": 385
    },
    {
      "name": "过程装备",
      "count": 379
    },
    {
      "name": "Z电子商务",
      "count": 363
    },
    {
      "name": "工商管理",
      "count": 348
    }
  ],
  "classStats": {
    "totalClasses": 1191,
    "avgSize": "32.0",
    "largest": [
      {
        "name": "数媒技术22-01",
        "count": 75
      },
      {
        "name": "工业软件23-01",
        "count": 70
      },
      {
        "name": "工业软件23-03",
        "count": 69
      },
      {
        "name": "工业软件23-04",
        "count": 69
      },
      {
        "name": "工业软件23-05",
        "count": 69
      },
      {
        "name": "工业软件23-06",
        "count": 69
      },
      {
        "name": "工业软件24-01",
        "count": 69
      },
      {
        "name": "工业软件24-02",
        "count": 69
      },
      {
        "name": "工业软件23-02",
        "count": 68
      },
      {
        "name": "工业软件24-03",
        "count": 68
      }
    ],
    "smallest": [
      {
        "name": "自动化类22-05",
        "count": 1
      },
      {
        "name": "自动化类22-03",
        "count": 1
      },
      {
        "name": "工商管理类22-04",
        "count": 1
      },
      {
        "name": "雕塑22-01",
        "count": 1
      },
      {
        "name": "设计学类21-16",
        "count": 1
      },
      {
        "name": "设计学类21-13",
        "count": 1
      },
      {
        "name": "Z汉语教育24-01",
        "count": 2
      },
      {
        "name": "Z国际经贸24-01",
        "count": 13
      },
      {
        "name": "市场营销22-02",
        "count": 16
      },
      {
        "name": "壁画21-01",
        "count": 16
      }
    ]
  },
  "uniqueNamesCount": 32186,
  "uniqueNamesPercent": "84.5",
  "interesting": {
    "sameCharNames": [
      "高亭亭",
      "庞冠冠",
      "黄莉莉",
      "董莹莹",
      "杜一一",
      "魏瑶瑶",
      "秦菁菁",
      "汪祯祯",
      "杨盼盼",
      "扶婷婷",
      "李鑫鑫",
      "王媛媛",
      "刘洋洋",
      "赵笑笑",
      "卞欢欢",
      "龚珊珊",
      "陈婷婷",
      "李圆圆",
      "朱媛媛",
      "程璐璐",
      "李佳佳",
      "陆娜娜",
      "邓可可",
      "陆笑笑",
      "杨金金",
      "王龙龙",
      "裴皓皓",
      "徐朋朋",
      "王元元",
      "郭珂珂",
      "杨钦钦",
      "肖鑫鑫",
      "齐甜甜",
      "易婷婷",
      "郑创创",
      "王点点",
      "任元元",
      "胡萌萌",
      "周君君",
      "吴莹莹",
      "马萌萌",
      "潘聪聪",
      "张晴晴",
      "王菲菲",
      "吴妮妮",
      "刘蓓蓓",
      "刘桃桃",
      "宋倩倩",
      "谭妹妹",
      "陈晶晶"
    ],
    "celebrityLikeNames": [
      "李俊杰",
      "何俊杰",
      "王俊杰",
      "江俊杰",
      "王菲",
      "孔德华",
      "刘小龙",
      "丁俊杰",
      "苏军",
      "李玲",
      "王云",
      "王歌",
      "赵俊杰",
      "龚俊杰",
      "张英",
      "袁一博",
      "贺俊杰",
      "韩龙",
      "彭歌",
      "李龙",
      "湛云",
      "张玲",
      "张一博",
      "曹小龙",
      "程龙",
      "简腾",
      "贾俊杰",
      "陈俊杰",
      "兰龙",
      "王腾"
    ],
    "abccNames": [
      "高亭亭",
      "庞冠冠",
      "黄莉莉",
      "董莹莹",
      "杜一一",
      "魏瑶瑶",
      "秦菁菁",
      "汪祯祯",
      "杨盼盼",
      "扶婷婷",
      "李鑫鑫",
      "王媛媛",
      "刘洋洋",
      "赵笑笑",
      "卞欢欢",
      "龚珊珊",
      "陈婷婷",
      "李圆圆",
      "朱媛媛",
      "程璐璐",
      "李佳佳",
      "陆娜娜",
      "邓可可",
      "陆笑笑",
      "杨金金",
      "王龙龙",
      "裴皓皓",
      "徐朋朋",
      "王元元",
      "郭珂珂"
    ],
    "aabcNames": []
  }
}